MANIFEST.in
PYPI.rst
README.md
setup.py
docs/LICENSE.md
src/dbDesigner/__init__.py
src/dbDesigner/protoDiagram.py
src/dbDesigner/protoDiagramEntity.py
src/dbDesigner/urls.py
src/dbDesigner/service/__init__.py
src/dbDesigner/service/diagramJSONAssembler.py
src/dbDesigner/service/diagramService.py
src/django_softmachine.egg-info/PKG-INFO
src/django_softmachine.egg-info/SOURCES.txt
src/django_softmachine.egg-info/dependency_links.txt
src/django_softmachine.egg-info/requires.txt
src/django_softmachine.egg-info/top_level.txt
src/protoLib/__init__.py
src/protoLib/fields.py
src/protoLib/models.py
src/protoLib/protoActionEdit.py
src/protoLib/protoActionList.py
src/protoLib/protoActionRep.py
src/protoLib/protoActions.py
src/protoLib/protoAuth.py
src/protoLib/protoField.py
src/protoLib/protoGetDetails.py
src/protoLib/protoGetPci.py
src/protoLib/protoGrid.py
src/protoLib/protoLogin.py
src/protoLib/protoMenu.py
src/protoLib/protoQbe.py
src/protoLib/urls.py
src/protoLib/usrDefProps.py
src/protoLib/utilsBase.py
src/protoLib/utilsConvert.py
src/protoLib/utilsDb.py
src/protoLib/utilsWeb.py
src/protoLib/actions/__init__.py
src/protoLib/actions/findReplace.py
src/protoLib/admin/__init__.py
src/protoLib/admin/adminOrgTree.py
src/protoLib/admin/adminProtoDef.py
src/protoLib/admin/adminUserProf.py
src/protoLib/admin/adminUsr.py
src/protoLib/localisation/__init__.py
src/protoLib/localisation/en.py
src/protoLib/localisation/es.py
src/protoLib/localisation/fr.py
src/protoLib/management/__init__.py
src/protoLib/utils/__init__.py
src/protoLib/utils/authPlugins.py
src/protoLib/utils/downloadFile.py
src/protoLib/utils/generic_views.py
src/protoLib/utils/loadFile.py
src/protoLib/utils/logger.py
src/protoLib/utils/modelsTools.py
src/protoLib/utils/xml2json.py
src/protobase/__init__.py
src/protobase/static/.DS_Store
src/protobase/static/app.jsb3
src/protobase/static/buildSenchaJS.sh
src/protobase/static/css/app.css
src/protobase/static/css/designer.css
src/protobase/static/css/print.css
src/protobase/static/css/printDGT.css
src/protobase/static/css/protoOrg.css
src/protobase/static/css/statusbar.css
src/protobase/static/help/champs.html
src/protobase/static/help/classer.html
src/protobase/static/help/configuration.html
