Metadata-Version: 1.1
Name: django-softmachine
Version: 1.0.6
Summary: CeRTAE SoftMachine est une application web qui consiste à réaliser les interfaces d’une application par la construction de vues à partir d’un modèle de données normalisée.
Home-page: https://github.com/certae/django-softmachine
Author: Certae - Dario Gomez Tafur
Author-email: dariogomeztw@gmail.com
License: GPL License, see docs/LICENCE.md
Platform: UNKNOWN
Classifier: Environment :: Web Environment
Classifier: Framework :: Django
Classifier: Intended Audience :: Developers
Classifier: License :: OSI Approved :: GNU General Public License (GPL)
Classifier: Operating System :: OS Independent
Classifier: Programming Language :: Python
Classifier: Programming Language :: Python :: 2.7
Classifier: Topic :: Internet :: WWW/HTTP
Classifier: Topic :: Internet :: WWW/HTTP :: Dynamic Content
